gitflow/__init__.py
gitflow/branches.py
gitflow/core.py
gitflow/exceptions.py
gitflow/util.py
gitflow/bin/__init__.py
gitflow/bin/_init.py
paige_gitflow-1.0.3.dist-info/AUTHORS.txt
paige_gitflow-1.0.3.dist-info/LICENSE.txt
paige_gitflow-1.0.3.dist-info/METADATA
paige_gitflow-1.0.3.dist-info/WHEEL
paige_gitflow-1.0.3.dist-info/entry_points.txt
paige_gitflow-1.0.3.dist-info/top_level.txt
paige_gitflow-1.0.3.dist-info/RECORD
